basen/__init__.py
basen/basen.py
basen/int2base.py
basen_encoder-1.0.2.dist-info/METADATA
basen_encoder-1.0.2.dist-info/WHEEL
basen_encoder-1.0.2.dist-info/licenses/LICENSE
basen_encoder-1.0.2.dist-info/RECORD
