Metadata-Version: 2.1
Name: basen-encoder
Version: 1.0.2
Summary: Custom encoder that encodes any binary data to given alphabet.
Keywords: generator base-encoder basen base base128 base64 base32 base16
Home-page: https://github.com/vd2org/basen
Author-Email: vd <basen@vd2.org>
License: MIT License
Classifier: Development Status :: 5 - Production/Stable
Classifier: Intended Audience :: Developers
Classifier: Intended Audience :: Education
Classifier: Intended Audience :: Information Technology
Classifier: License :: OSI Approved :: MIT License
Classifier: Operating System :: OS Independent
Classifier: Programming Language :: Python :: 3.8
Classifier: Programming Language :: Python :: 3.9
Classifier: Programming Language :: Python :: 3.10
Classifier: Programming Language :: Python :: 3.11
Classifier: Programming Language :: Python :: 3.12
Classifier: Programming Language :: Python :: 3 :: Only
Classifier: Topic :: Utilities
Classifier: Topic :: Software Development
Classifier: Topic :: Software Development :: Libraries
Classifier: Topic :: Software Development :: Libraries :: Python Modules
Project-URL: Homepage, https://github.com/vd2org/basen
Project-URL: Repository, https://github.com/vd2org/basen.git
Project-URL: Issues, https://github.com/vd2org/basen/issues
Requires-Python: <3.13,>=3.8
